ztool/__init__.py
ztool-0.0.2.dist-info/METADATA
ztool-0.0.2.dist-info/WHEEL
ztool-0.0.2.dist-info/license.txt
ztool-0.0.2.dist-info/top_level.txt
ztool-0.0.2.dist-info/RECORD
