Metadata-Version: 2.1
Name: ztool
Version: 0.0.2
Summary: ToolBox for Python
Home-page: https://pypi.org/project/ztool/
Author: Zhong Yufeng
Author-email: zhong.yufeng@foxmail.com
License: MIT
Platform: any
Classifier: Programming Language :: Python :: 3
Classifier: Programming Language :: Python :: 3.6
Classifier: Programming Language :: Python :: 3.7
Classifier: Programming Language :: Python :: 3.8
Classifier: Operating System :: OS Independent
Classifier: License :: OSI Approved :: MIT License
Requires-Python: >=3
License-File: license.txt
